maccel/__init__.py
maccel/accelerator.py
maccel/future.py
maccel/maccel.cp311-win_amd64.pyd
maccel/model.py
maccel/model_variant_handle.py
maccel/type.py
maccel/version.py
maccel-0.30.1.dist-info/METADATA
maccel-0.30.1.dist-info/WHEEL
maccel-0.30.1.dist-info/top_level.txt
maccel-0.30.1.dist-info/RECORD
