Metadata-Version: 2.4
Name: maccel
Version: 0.30.1
Requires-Dist: numpy<1.20; python_version < "3.7"
Requires-Dist: numpy; python_version >= "3.7"
Dynamic: requires-dist
